Metadata-Version: 1.0
Name: mkdocs-basic-theme
Version: 1.0.1
Summary: Minimal theme for MkDocs
Home-page: https://github.com/mkdocs/mkdocs-basic-theme
Author: Dougal Matthews
Author-email: dougal@dougalmatthews.com.com
License: BSD
Platform: UNKNOWN
